adafruit_turtle.py
adafruit_circuitpython_turtle-3.1.9.dist-info/licenses/LICENSE
adafruit_circuitpython_turtle-3.1.9.dist-info/METADATA
adafruit_circuitpython_turtle-3.1.9.dist-info/WHEEL
adafruit_circuitpython_turtle-3.1.9.dist-info/top_level.txt
adafruit_circuitpython_turtle-3.1.9.dist-info/RECORD
