Metadata-Version: 2.4
Name: adafruit-circuitpython-turtle
Version: 3.1.9
Summary: Turtle graphics library for CircuitPython and displayio
Author-email: Adafruit Industries <circuitpython@adafruit.com>
License: MIT
Project-URL: Homepage, https://github.com/adafruit/Adafruit_CircuitPython_turtle
Keywords: adafruit,blinka,circuitpython,micropython,turtle,graphics,turtle
Classifier: Intended Audience :: Developers
Classifier: Topic :: Software Development :: Libraries
Classifier: Topic :: Software Development :: Embedded Systems
Classifier: Topic :: System :: Hardware
Classifier: License :: OSI Approved :: MIT License
Classifier: Programming Language :: Python :: 3
License-File: LICENSE
Requires-Dist: Adafruit-Blinka
Provides-Extra: optional
Dynamic: license-file
